LICENSE
MANIFEST.in
requirements.txt
setup.py
bin/OANDAd
etc/OANDA/config/OANDAd.cfg
etc/OANDA/config/plugins/plainfile.cfg
etc/OANDA/config/plugins/pubsub.cfg
etc/OANDA/config/plugins/example/mysql.cfg
etc/OANDA/plugins/README.md
etc/OANDA/plugins/plainfile.py
etc/OANDA/plugins/pubsub.py
etc/OANDA/plugins/example/mysql.py
oanda_trading_environment/__init__.py
oanda_trading_environment.egg-info/PKG-INFO
oanda_trading_environment.egg-info/SOURCES.txt
oanda_trading_environment.egg-info/dependency_links.txt
oanda_trading_environment.egg-info/entry_points.txt
oanda_trading_environment.egg-info/requires.txt
oanda_trading_environment.egg-info/top_level.txt
oanda_trading_environment/daemon/__init__.py
oanda_trading_environment/daemon/plugin.py
oanda_trading_environment/stream/__init__.py
oanda_trading_environment/stream/candlefactory.py
oanda_trading_environment/stream/parser.py
oanda_trading_environment/stream/parserV20.py
oanda_trading_environment/stream/streamrecord.py