Metadata-Version: 1.1
Name: oanda-trading-environment
Version: 0.3.0
Summary: OANDA REST-API based environment serving as a base for futher development of trading tools. Main part is the OANDAd daemon processing the streaming quotes
Home-page: https://github.com/hootnot/oanda-trading-environment
Author: Feite Brekeveld
Author-email: f.brekeveld@gmail.com
License: MIT
Keywords: Python OANDA oandapy REST API trading modules
Platform: UNKNOWN
Classifier: Development Status :: 4 - Beta
Classifier: Intended Audience :: Developers
Classifier: Intended Audience :: Financial and Insurance Industry
Classifier: Operating System :: POSIX :: Linux
Classifier: Programming Language :: Python
Classifier: Topic :: Software Development :: Libraries :: Python Modules
